floatingtime/__init__.py
floatingtime/main.py
floatingtime/time_window.py
floatingtime-1.5.0.dist-info/METADATA
floatingtime-1.5.0.dist-info/WHEEL
floatingtime-1.5.0.dist-info/licenses/LICENSE
floatingtime-1.5.0.dist-info/RECORD
